test/__init__.py
test/test_engine.py
test/templates/__init__.py
test/templates/test_json.py
test/templates/test_pickle.py
test/templates/test_registry.py
xmem/__init__.py
xmem/engine.py
xmem/exceptions.py
xmem/template.py
xmem/templates/__init__.py
xmem/templates/json.py
xmem/templates/pickle.py
xmem/templates/registry.py
xmem-0.1.1.dist-info/LICENSE
xmem-0.1.1.dist-info/METADATA
xmem-0.1.1.dist-info/WHEEL
xmem-0.1.1.dist-info/top_level.txt
xmem-0.1.1.dist-info/RECORD
