Metadata-Version: 2.1
Name: xmem
Version: 0.1.1
Summary: A simple, light, easy-to-use, and extensible memory module
Home-page: https://github.com/mHaisham/xmem
Author: Schicksal
Author-email: mhaisham79@gmail.com
License: MIT license
Keywords: memory storage json pickle extensible light
Platform: UNKNOWN
Classifier: License :: OSI Approved :: MIT License
Classifier: Programming Language :: Python :: 3.6
Classifier: Operating System :: OS Independent
Requires-Python: >=3.6
